camtest/__init__.py
camtest/__main__.py
camtest/settings.yaml
camtest/version.py
camtest/analysis/CAM-TVPT-090-ghosts_data-reduction-simulations.py
camtest/analysis/CAM-TVPT-090-ghosts_data-reduction.py
camtest/analysis/CAM-TVPT-090-ghosts_data-reduction_IAS.py
camtest/analysis/CAM-TVPT_110_image_geometry_test.py
camtest/analysis/CAM_TVPT_010_best_focus_analysis.py
camtest/analysis/CAM_TVPT_010_best_focus_analysis_martin.py
camtest/analysis/CAM_TVPT_050_autocompatibility.py
camtest/analysis/CAM_TVPT_050_autocompatibility_utilities.py
camtest/analysis/CAM_TVPT_110_image_geometry.py
camtest/analysis/analysis_SFT.py
camtest/analysis/analysis_ambient_hartmann_THs.py
camtest/analysis/analysis_ambient_recentering.py
camtest/analysis/analysis_fpa_eidp_ccd_corners.py
camtest/analysis/analysis_mgse_stages_synchro_csl.py
camtest/analysis/cam_tvlpt_030_test_673_dark_ncam_sim.py
camtest/analysis/cam_tvpt_031_psf_at_nominal_focus.py
camtest/analysis/cam_tvpt_031_tools.py
camtest/analysis/cam_tvpt_045_CCD_characterization_dark_only_dmw.py
camtest/analysis/cam_tvpt_045_CCD_characterization_dark_only_noise_hotpix_dmw.py
camtest/analysis/cam_tvpt_045_CCD_characterization_temperatures_dmw.py
camtest/analysis/cam_tvpt_080_dynamic_range_analysis.py
camtest/analysis/convenience.py
camtest/analysis/find_sources.py
camtest/analysis/fits_per_layer.py
camtest/analysis/hartmann_circle_reduction.py
camtest/analysis/hartmann_verification_reduction.py
camtest/analysis/image_utils.py
camtest/analysis/observation.py
camtest/analysis/quick_ghost_analysis_local.py
camtest/analysis/quick_look_obsid.py
camtest/analysis/quick_psf-size_analysis.py
camtest/analysis/setup_fee_limits.py
camtest/analysis/setup_ron_offsets.py
camtest/analysis/simfits.py
camtest/analysis/valid_cubes.py
camtest/analysis/functions/fitsfiles.py
camtest/analysis/functions/fov_utils.py
camtest/analysis/functions/hartmann_fov_path_optimisation.py
camtest/analysis/functions/hartmann_utils.py
camtest/analysis/functions/hk_utils.py
cgse_ts-2024.7.0.dist-info/LICENSE
cgse_ts-2024.7.0.dist-info/METADATA
cgse_ts-2024.7.0.dist-info/WHEEL
cgse_ts-2024.7.0.dist-info/entry_points.txt
cgse_ts-2024.7.0.dist-info/top_level.txt
cgse_ts-2024.7.0.dist-info/RECORD
