Metadata-Version: 2.1
Name: cgse-ts
Version: 2024.7.0
Summary: PLATO Common-EGSE Test Scripts
Author-email: Rik Huygen <rik.huygen@kuleuven.be>, Sara Regibo <sara.regibo@kuleuven.be>
Maintainer: Pierre Royer, Nicolas Beraud, Sena Gomashie, Jesus Saiz
License: LGPL-3.0
Project-URL: documentation, https://ivs-kuleuven.github.io/plato-cgse-doc/
Project-URL: repository, https://github.com/IvS-KULeuven/plato-test-scripts
Keywords: CGSE,PLATO,test scripts
Classifier: Development Status :: 5 - Production/Stable
Classifier: Programming Language :: Python :: 3.8
Classifier: License :: OSI Approved :: GNU Lesser General Public License v3 (LGPLv3)
Requires-Python: >=3.8
License-File: LICENSE
Requires-Dist: cgse >=2024.7.0
Requires-Dist: gui-executor >=0.18.3
Requires-Dist: sep
Requires-Dist: scikit-image
Requires-Dist: scikit-learn
